convert_markdown/__init__.py
convert_markdown/__main__.py
convert_markdown/cli.py
convert_markdown/converter.py
convert_markdown/docx_generator.py
convert_markdown/utils/__init__.py
convert_markdown/utils/markdown_utils.py
convert_markdown_docx-0.1.2.dist-info/LICENSE
convert_markdown_docx-0.1.2.dist-info/METADATA
convert_markdown_docx-0.1.2.dist-info/WHEEL
convert_markdown_docx-0.1.2.dist-info/entry_points.txt
convert_markdown_docx-0.1.2.dist-info/RECORD
