Metadata-Version: 2.3
Name: convert-markdown-docx
Version: 0.1.2
Summary: Converte arquivos Markdown para DOCX formatado em ABNT.
License: MIT
Keywords: markdown,docx,abnt,python-docx
Author: Brayan Pletsch
Author-email: brayan.pletsch@gmail.com
Requires-Python: >=3.8,<4.0
Classifier: Development Status :: 4 - Beta
Classifier: License :: OSI Approved :: MIT License
Classifier: Programming Language :: Python :: 3
Classifier: Programming Language :: Python :: 3.8
Classifier: Programming Language :: Python :: 3.9
Classifier: Programming Language :: Python :: 3.10
Classifier: Programming Language :: Python :: 3.11
Classifier: Programming Language :: Python :: 3.12
Classifier: Programming Language :: Python :: 3.13
Classifier: Topic :: Text Processing :: Markup :: Markdown
Requires-Dist: lxml (==5.3.2)
Requires-Dist: python-docx (==1.1.2)
Requires-Dist: typing_extensions (==4.13.2)
Project-URL: Bug Tracker, https://github.com/BrayanPletsch/ConvertMarkdownToDocx/issues
Project-URL: Documentation, https://github.com/BrayanPletsch/ConvertMarkdownToDocx#readme
Project-URL: Homepage, https://github.com/BrayanPletsch/ConvertMarkdownToDocx
Project-URL: Repository, https://github.com/BrayanPletsch/ConvertMarkdownToDocx
